awc/__init__.py
awc/__main__.py
awc/api.py
awc/const.py
awc/exc.py
awc/py.typed
awc/util.py
awc/wrn.py
awc/sql/__init__.py
awc/sql/helpers.py
awc-3.2.0.dist-info/LICENSE
awc-3.2.0.dist-info/METADATA
awc-3.2.0.dist-info/WHEEL
awc-3.2.0.dist-info/top_level.txt
awc-3.2.0.dist-info/zip-safe
awc-3.2.0.dist-info/RECORD
