Metadata-Version: 2.1
Name: awc
Version: 3.2.0
Summary: wrapper for ari-web comments API
Home-page: https://ari-web.xyz/gh/awc
Author: Ari Archer
Author-email: ari.web.xyz@gmail.com
License: GPLv3+
Keywords: http,http-client,comments,api,wrapper,https
Classifier: Development Status :: 5 - Production/Stable
Classifier: Intended Audience :: Developers
Classifier: License :: OSI Approved :: GNU General Public License v3 or later (GPLv3+)
Classifier: Operating System :: OS Independent
Classifier: Programming Language :: Python :: 3
Classifier: Programming Language :: Python :: 3.8
Classifier: Programming Language :: Python :: 3.9
Classifier: Programming Language :: Python :: 3.10
Classifier: Programming Language :: Python :: 3.11
Classifier: Programming Language :: Python :: 3.12
Classifier: Topic :: Internet :: WWW/HTTP
Classifier: Topic :: Software Development :: Libraries :: Python Modules
Classifier: Typing :: Typed
License-File: LICENSE
Requires-Dist: requests
Requires-Dist: types-requests
Requires-Dist: types-sqlalchemy
Requires-Dist: furl
Requires-Dist: pypika
